cultivate/__init__.py
cultivate-0.0.0.dist-info/METADATA
cultivate-0.0.0.dist-info/WHEEL
cultivate-0.0.0.dist-info/top_level.txt
cultivate-0.0.0.dist-info/RECORD
