Metadata-Version: 2.4
Name: cultivate
Version: 0.0.0
Summary: Coming soon
Author-email: "Nicholas H.Tollervey" <ntoll@ntoll.org>
